setup.py
userapp/__init__.py
userapp.egg-info/PKG-INFO
userapp.egg-info/SOURCES.txt
userapp.egg-info/dependency_links.txt
userapp.egg-info/not-zip-safe
userapp.egg-info/requires.txt
userapp.egg-info/top_level.txt